__init__.py
_version.py
unified_interface.py
config/__init__.py
config/indicators.py
core/__init__.py
core/downloader.py
core/extractor.py
data/__init__.py
data/parser.py
data/standardizer.py
data/validator.py
interpolation/__init__.py
interpolation/alpha_shape.py
interpolation/convex_hull.py
interpolation/density_boundary.py
interpolation/enhanced_interpolation.py
utils/__init__.py
utils/logger.py
visualization/__init__.py
visualization/color_mapper.py
visualization/layout_calculator.py
visualization/svg_generator.py
svg_water_quality_generator-1.0.0.dist-info/METADATA
svg_water_quality_generator-1.0.0.dist-info/WHEEL
svg_water_quality_generator-1.0.0.dist-info/top_level.txt
svg_water_quality_generator-1.0.0.dist-info/RECORD
