Metadata-Version: 2.4
Name: svg-water-quality-generator
Version: 1.0.0
Summary: 专用于从水质监测数据生成SVG热力图的独立Python库
Requires-Python: >=3.11
Requires-Dist: chardet>=5.2.0
Requires-Dist: matplotlib>=3.10.3
Requires-Dist: numpy>=2.3.1
Requires-Dist: pandas>=2.3.1
Requires-Dist: pillow>=11.3.0
Requires-Dist: python-dotenv>=1.1.1
Requires-Dist: requests>=2.32.4
Requires-Dist: scipy>=1.16.0
